[
    {
        "client_msg_id": "a9419c70-f402-4dfc-b961-139ed39442dc",
        "type": "message",
        "text": "Victoria has shown me some demos of the stuff they're doing at Adobe. Really cool stuff! 3D capture is a great way to lower the technical bar for making animations.",
        "user": "UD43R8ZFV",
        "ts": "1550786027.000100",
        "team": "T5TCAFTA9",
        "user_team": "T5TCAFTA9",
        "source_team": "T5TCAFTA9",
        "user_profile": {
            "avatar_hash": "85ee3dacef95",
            "image_72": "https:\/\/avatars.slack-edge.com\/2018-09-30\/445630960161_85ee3dacef95dd5617e4_72.png",
            "first_name": "Tim",
            "real_name": "Tim Swast",
            "display_name": "",
            "team": "T5TCAFTA9",
            "name": "tswast",
            "is_restricted": false,
            "is_ultra_restricted": false
        },
        "thread_ts": "1550516704.010000",
        "parent_user_id": "UDLGND5GA"
    }
]