[
    {
        "client_msg_id": "21587ae5-0eb3-41c5-911a-bcbb96a586b0",
        "type": "message",
        "text": "Also, digging through some internet backwaters for references, I found this old mailing list \u2014 <https://groups.google.com/g/philosophy-in-a-time-of-software>\n\nMade me wonder if anyone who used to hang out there is now here.",
        "user": "UC2A2ARPT",
        "ts": "1685836794.743269",
        "blocks": [
            {
                "type": "rich_text",
                "block_id": "Yqg",
                "elements": [
                    {
                        "type": "rich_text_section",
                        "elements": [
                            {
                                "type": "text",
                                "text": "Also, digging through some internet backwaters for references, I found this old mailing list \u2014 "
                            },
                            {
                                "type": "link",
                                "url": "https://groups.google.com/g/philosophy-in-a-time-of-software"
                            },
                            {
                                "type": "text",
                                "text": "\n\nMade me wonder if anyone who used to hang out there is now here."
                            }
                        ]
                    }
                ]
            }
        ],
        "team": "T5TCAFTA9",
        "thread_ts": "1685836794.743269",
        "reply_count": 2,
        "reply_users_count": 2,
        "latest_reply": "1685901690.512179",
        "reply_users": [
            "USH01JEDQ",
            "UF71PR58X"
        ],
        "is_locked": false,
        "subscribed": false,
        "reactions": [
            {
                "name": "heart",
                "users": [
                    "USH01JEDQ",
                    "U03R0B9U1GD"
                ],
                "count": 2
            }
        ]
    },
    {
        "client_msg_id": "20F769CB-1ADE-493C-8DD2-8D2C55411161",
        "type": "message",
        "text": "Would have been there if I knew\n\n85 total posts, group deserved greater mass",
        "user": "USH01JEDQ",
        "ts": "1685892171.670039",
        "blocks": [
            {
                "type": "rich_text",
                "block_id": "RJFo0",
                "elements": [
                    {
                        "type": "rich_text_section",
                        "elements": [
                            {
                                "type": "text",
                                "text": "Would have been there if I knew\n\n85 total posts, group deserved greater mass"
                            }
                        ]
                    }
                ]
            }
        ],
        "team": "T5TCAFTA9",
        "thread_ts": "1685836794.743269",
        "parent_user_id": "UC2A2ARPT"
    },
    {
        "client_msg_id": "6F46C022-26C5-42EE-AF9F-B82A5D868D7C",
        "type": "message",
        "text": "\u201cCommunal computing for 21st century science, Apr 2023\u201d\n\n<https://m.youtube.com/watch?v=-80VsIdAHZw&amp;feature=youtu.be|https://m.youtube.com/watch?v=-80VsIdAHZw&amp;feature=youtu.be>",
        "user": "U0378MDUG1Y",
        "ts": "1685895424.155509",
        "blocks": [
            {
                "type": "rich_text",
                "block_id": "S+I",
                "elements": [
                    {
                        "type": "rich_text_section",
                        "elements": [
                            {
                                "type": "text",
                                "text": "\u201cCommunal computing for 21st century science, Apr 2023\u201d\n\n"
                            },
                            {
                                "type": "link",
                                "url": "https://m.youtube.com/watch?v=-80VsIdAHZw&feature=youtu.be",
                                "text": "https://m.youtube.com/watch?v=-80VsIdAHZw&feature=youtu.be"
                            }
                        ]
                    }
                ]
            }
        ],
        "team": "T5TCAFTA9",
        "attachments": [
            {
                "from_url": "https://m.youtube.com/watch?v=-80VsIdAHZw&amp;feature=youtu.be",
                "thumb_url": "https://i.ytimg.com/vi/-80VsIdAHZw/hqdefault.jpg",
                "thumb_width": 480,
                "thumb_height": 360,
                "video_html": "<iframe width=\"400\" height=\"225\" src=\"https://www.youtube.com/embed/-80VsIdAHZw?feature=oembed&autoplay=1&iv_load_policy=3\" frameborder=\"0\" allow=\"accelerometer; autoplay; clipboard-write; encrypted-media; gyroscope; picture-in-picture; web-share\" allowfullscreen title=\"Communal computing for 21st century science, Apr 2023\"></iframe>",
                "video_html_width": 400,
                "video_html_height": 225,
                "service_icon": "https://a.slack-edge.com/80588/img/unfurl_icons/youtube.png",
                "id": 1,
                "original_url": "https://m.youtube.com/watch?v=-80VsIdAHZw&amp;feature=youtu.be",
                "fallback": "YouTube Video: Communal computing for 21st century science, Apr 2023",
                "title": "Communal computing for 21st century science, Apr 2023",
                "title_link": "https://m.youtube.com/watch?v=-80VsIdAHZw&amp;feature=youtu.be",
                "author_name": "Dynamicland",
                "author_link": "https://www.youtube.com/@dynamicland1784",
                "service_name": "YouTube",
                "service_url": "https://www.youtube.com/"
            }
        ],
        "thread_ts": "1685895424.155509",
        "reply_count": 1,
        "reply_users_count": 1,
        "latest_reply": "1685897424.154429",
        "reply_users": [
            "U03CEGR3HSL"
        ],
        "is_locked": false,
        "subscribed": false,
        "reactions": [
            {
                "name": "white_check_mark",
                "users": [
                    "UGWUJUZHT"
                ],
                "count": 1
            },
            {
                "name": "eyes",
                "users": [
                    "UC2A2ARPT"
                ],
                "count": 1
            }
        ]
    },
    {
        "client_msg_id": "12ff2556-131f-46ae-b7c5-e85a8a642b46",
        "type": "message",
        "text": "I've seen a lot of cool Dynamicland demos, but I'm not sure how this will actually improve the world as long as it is locked up in one research lab, where nobody else can work with it.\n\nI've read descriptions of their concerns about not wanting a reduced and misunderstood version of their ideas to take root in the wider culture, as happened with the Xerox PARC research.\n\nI would argue that the reason a reduced and misunderstood version of the PARC research took root in the popular culture was because most people were not exposed to the real thing. They were exposed to Apple's and Microsoft's crappy copy of a superficial understanding of the surface appearance of the PARC research.\n\nBy keeping Dynamicland so proprietary and under wraps, I fear that Victor is probably going to end up recreating this same tragedy, when someone who watches the video demos creates a crappy copy of a superficial understanding of the surface appearance of the Dynamicland research, and that crappy copy takes root in the popular culture.",
        "user": "U03CEGR3HSL",
        "ts": "1685897424.154429",
        "blocks": [
            {
                "type": "rich_text",
                "block_id": "YL3PF",
                "elements": [
                    {
                        "type": "rich_text_section",
                        "elements": [
                            {
                                "type": "text",
                                "text": "I've seen a lot of cool Dynamicland demos, but I'm not sure how this will actually improve the world as long as it is locked up in one research lab, where nobody else can work with it.\n\nI've read descriptions of their concerns about not wanting a reduced and misunderstood version of their ideas to take root in the wider culture, as happened with the Xerox PARC research.\n\nI would argue that the reason a reduced and misunderstood version of the PARC research took root in the popular culture was because most people were not exposed to the real thing. They were exposed to Apple's and Microsoft's crappy copy of a superficial understanding of the surface appearance of the PARC research.\n\nBy keeping Dynamicland so proprietary and under wraps, I fear that Victor is probably going to end up recreating this same tragedy, when someone who watches the video demos creates a crappy copy of a superficial understanding of the surface appearance of the Dynamicland research, and that crappy copy takes root in the popular culture."
                            }
                        ]
                    }
                ]
            }
        ],
        "team": "T5TCAFTA9",
        "thread_ts": "1685895424.155509",
        "parent_user_id": "U0378MDUG1Y"
    },
    {
        "client_msg_id": "873f6508-ddb7-43a8-bb33-b4887bafe108",
        "type": "message",
        "text": "Subscribed (still subscribed apparently!) but I think it was already almost dormant by the time I found it.",
        "user": "UF71PR58X",
        "ts": "1685901690.512179",
        "blocks": [
            {
                "type": "rich_text",
                "block_id": "K9g",
                "elements": [
                    {
                        "type": "rich_text_section",
                        "elements": [
                            {
                                "type": "text",
                                "text": "Subscribed (still subscribed apparently!) but I think it was already almost dormant by the time I found it."
                            }
                        ]
                    }
                ]
            }
        ],
        "team": "T5TCAFTA9",
        "thread_ts": "1685836794.743269",
        "parent_user_id": "UC2A2ARPT"
    }
]