[
    {
        "client_msg_id": "ae23d371-ff5d-4d6a-8e0a-88f0268eefd3",
        "type": "message",
        "text": "Papers We Love - <https://paperswelove.org/|https://paperswelove.org/>",
        "user": "UPVBV34EL",
        "ts": "1640869637.219300",
        "team": "T5TCAFTA9",
        "blocks": [
            {
                "type": "rich_text",
                "block_id": "G9c",
                "elements": [
                    {
                        "type": "rich_text_section",
                        "elements": [
                            {
                                "type": "text",
                                "text": "Papers We Love - "
                            },
                            {
                                "type": "link",
                                "url": "https://paperswelove.org/",
                                "text": "https://paperswelove.org/"
                            }
                        ]
                    }
                ]
            }
        ],
        "thread_ts": "1640869637.219300",
        "reply_count": 1,
        "reply_users_count": 1,
        "latest_reply": "1641104994.228600",
        "reply_users": [
            "U01UEG1GYMT"
        ],
        "is_locked": false,
        "subscribed": false
    },
    {
        "client_msg_id": "ce7112f0-f328-4003-9e1d-a88e79f34f95",
        "type": "message",
        "text": ":warning:\n\nReminder for folks posting to this channel \u2014 please include an excerpt or summary of your link in the text of your message. Don't rely on the Slack-generated previews, as they're typically low-quality, occasionally totally irrelevant, inaccessible for folks using the <http://history.futureofcoding.org|history search> (and perhaps non-standard clients), and (thus) very likely to be removed.\n\nIf you've posted here recently (this week), feel free to edit your message to include a summary or excerpt.",
        "user": "UC2A2ARPT",
        "ts": "1640885648.222600",
        "team": "T5TCAFTA9",
        "edited": {
            "user": "UC2A2ARPT",
            "ts": "1640896745.000000"
        },
        "blocks": [
            {
                "type": "rich_text",
                "block_id": "b2qd",
                "elements": [
                    {
                        "type": "rich_text_section",
                        "elements": [
                            {
                                "type": "emoji",
                                "name": "warning"
                            },
                            {
                                "type": "text",
                                "text": "\n\nReminder for folks posting to this channel \u2014 please include an excerpt or summary of your link in the text of your message. Don't rely on the Slack-generated previews, as they're typically low-quality, occasionally totally irrelevant, inaccessible for folks using the "
                            },
                            {
                                "type": "link",
                                "url": "http://history.futureofcoding.org",
                                "text": "history search"
                            },
                            {
                                "type": "text",
                                "text": " (and perhaps non-standard clients), and (thus) very likely to be removed.\n\nIf you've posted here recently (this week), feel free to edit your message to include a summary or excerpt."
                            }
                        ]
                    }
                ]
            }
        ],
        "reactions": [
            {
                "name": "heart",
                "users": [
                    "U02M6PM725T",
                    "U02E4DAQGSZ",
                    "U9C92716C",
                    "UPX3PH28N",
                    "U013ZLJARC7"
                ],
                "count": 5
            }
        ]
    },
    {
        "client_msg_id": "60b83b04-ecc4-481d-90b1-d2171098988d",
        "type": "message",
        "text": "\"Papers We Love (PWL) is a community built around reading, discussing and learning more about academic computer science papers.\"\n<https://github.com/papers-we-love/papers-we-love|https://github.com/papers-we-love/papers-we-love>",
        "user": "U01UEG1GYMT",
        "ts": "1641104994.228600",
        "team": "T5TCAFTA9",
        "blocks": [
            {
                "type": "rich_text",
                "block_id": "5fVs",
                "elements": [
                    {
                        "type": "rich_text_section",
                        "elements": [
                            {
                                "type": "text",
                                "text": "\"Papers We Love (PWL) is a community built around reading, discussing and learning more about academic computer science papers.\"\n"
                            },
                            {
                                "type": "link",
                                "url": "https://github.com/papers-we-love/papers-we-love",
                                "text": "https://github.com/papers-we-love/papers-we-love"
                            }
                        ]
                    }
                ]
            }
        ],
        "thread_ts": "1640869637.219300",
        "parent_user_id": "UPVBV34EL"
    }
]